[{"stop":{"id":"1:2919","code":"2919","name":"Kveda Melotineta Settlement","lat":41.657377,"lon":44.911989,"vehicleMode":"BUS"},"patternSuffixes":["0:01"]},{"stop":{"id":"1:3479","code":"3479","name":"Maria Perini Street","lat":41.657762,"lon":44.909768,"vehicleMode":"BUS"},"patternSuffixes":["0:01"]},{"stop":{"id":"1:2920","code":"2920","name":"Gaioz Rectori Street","lat":41.658918,"lon":44.905205,"vehicleMode":"BUS"},"patternSuffixes":["0:01"]},{"stop":{"id":"1:3482","code":"3482","name":"Dositeos Kutateli Street","lat":41.659792,"lon":44.901204,"vehicleMode":"BUS"},"patternSuffixes":["0:01"]},{"stop":{"id":"1:3485","code":"3485","name":"Emir Burjanadze St #24","lat":41.661705,"lon":44.896677,"vehicleMode":"BUS"},"patternSuffixes":["0:01"]},{"stop":{"id":"1:1045","code":"1045","name":"Nakaduli Street","lat":41.663004,"lon":44.894155,"vehicleMode":"BUS"},"patternSuffixes":["0:01"]},{"stop":{"id":"1:1039","code":"1039","name":"Saint Barbare Cemetery","lat":41.664733,"lon":44.890665,"vehicleMode":"BUS"},"patternSuffixes":["0:01"]},{"stop":{"id":"1:1042","code":"1042","name":"Public School #106","lat":41.670159,"lon":44.882377,"vehicleMode":"BUS"},"patternSuffixes":["0:01"]},{"stop":{"id":"1:1038","code":"1038","name":"Bogdan Khmelnitski St #7","lat":41.672016,"lon":44.8783,"vehicleMode":"BUS"},"patternSuffixes":["0:01"]},{"stop":{"id":"1:1036","code":"1036","name":"Bogdan Khmelnitski St #3","lat":41.671363,"lon":44.875765,"vehicleMode":"BUS"},"patternSuffixes":["0:01"]},{"stop":{"id":"1:3017","code":"3017","name":"Beri Gabriel Salosi Ave #169","lat":41.670792,"lon":44.871863,"vehicleMode":"BUS"},"patternSuffixes":["0:01"]},{"stop":{"id":"1:1032","code":"1032","name":"Beri Gabriel Salosi Ave #136","lat":41.672114,"lon":44.867542,"vehicleMode":"BUS"},"patternSuffixes":["0:01"]},{"stop":{"id":"1:1029","code":"1029","name":"Beri Gabriel Salosi Ave #120","lat":41.673132,"lon":44.862159,"vehicleMode":"BUS"},"patternSuffixes":["0:01"]},{"stop":{"id":"1:1027","code":"1027","name":"Shota Nadirashvili Street","lat":41.674172,"lon":44.856703,"vehicleMode":"BUS"},"patternSuffixes":["0:01"]},{"stop":{"id":"1:4243","code":"4243","name":"Public School #99","lat":41.675588,"lon":44.852339,"vehicleMode":"BUS"},"patternSuffixes":["0:01"]},{"stop":{"id":"1:3014","code":"3014","name":"Beri Gabriel Salosi Ave #52","lat":41.676063,"lon":44.849236,"vehicleMode":"BUS"},"patternSuffixes":["0:01"]},{"stop":{"id":"1:1025","code":"1025","name":"Bolnisi Street","lat":41.676534,"lon":44.844268,"vehicleMode":"BUS"},"patternSuffixes":["0:01"]},{"stop":{"id":"1:1947","code":"1947","name":"Beri Gabriel Salosi Square","lat":41.676893,"lon":44.840127,"vehicleMode":"BUS"},"patternSuffixes":["0:01"]},{"stop":{"id":"1:1021","code":"1021","name":"Gabriel Salosi Square","lat":41.677457,"lon":44.838852,"vehicleMode":"BUS"},"patternSuffixes":["0:01"]},{"stop":{"id":"1:2724","code":"2724","name":"Richard Holdbrook Street","lat":41.679677,"lon":44.838156,"vehicleMode":"BUS"},"patternSuffixes":["0:01"]},{"stop":{"id":"1:1019","code":"1019","name":"Navtlughi Street","lat":41.681745,"lon":44.839322,"vehicleMode":"BUS"},"patternSuffixes":["0:01"]},{"stop":{"id":"1:4584","code":"4584","name":"M/S Isani","lat":41.686468,"lon":44.83992,"vehicleMode":"BUS"},"patternSuffixes":["0:01"]},{"stop":{"id":"1:1016","code":"1016","name":"Public School #87","lat":41.686883,"lon":44.836372,"vehicleMode":"BUS"},"patternSuffixes":["0:01"]},{"stop":{"id":"1:1014","code":"1014","name":"Lech Kaczynski","lat":41.687166,"lon":44.833969,"vehicleMode":"BUS"},"patternSuffixes":["0:01"]},{"stop":{"id":"1:2123","code":"2123","name":"Public School #96","lat":41.687475,"lon":44.830412,"vehicleMode":"BUS"},"patternSuffixes":["0:01"]},{"stop":{"id":"1:4351","code":"4351","name":"M/S \"300 Aragveli\"","lat":41.687473,"lon":44.8274,"vehicleMode":"BUS"},"patternSuffixes":["0:01"]},{"stop":{"id":"1:4348","code":"4348","name":"Public School #89","lat":41.687502,"lon":44.824994,"vehicleMode":"BUS"},"patternSuffixes":["0:01"]},{"stop":{"id":"1:4324","code":"4324","name":"Public School #202 the Visually Impaired","lat":41.689276,"lon":44.820461,"vehicleMode":"BUS"},"patternSuffixes":["0:01"]},{"stop":{"id":"1:4344","code":"4344","name":"M/S \"Avlabari\"","lat":41.692142,"lon":44.814909,"vehicleMode":"BUS"},"patternSuffixes":["0:01"]},{"stop":{"id":"1:824","code":"824","name":"Nikoloz Baratashvili Street","lat":41.696663,"lon":44.804746,"vehicleMode":"BUS"},"patternSuffixes":["0:01"]},{"stop":{"id":"1:822","code":"822","name":"Freedom Square","lat":41.694033,"lon":44.801559,"vehicleMode":"BUS"},"patternSuffixes":["0:01"]},{"stop":{"id":"1:819","code":"819","name":"Tbilisi First Public School","lat":41.698033,"lon":44.798617,"vehicleMode":"BUS"},"patternSuffixes":["0:01"]},{"stop":{"id":"1:817","code":"817","name":"Opera Theater","lat":41.700768,"lon":44.795693,"vehicleMode":"BUS"},"patternSuffixes":["0:01"]},{"stop":{"id":"1:815","code":"815","name":"M/S \"Rustaveli\"","lat":41.70334,"lon":44.791208,"vehicleMode":"BUS"},"patternSuffixes":["0:01"]},{"stop":{"id":"1:4358","code":"4358","name":"Tbilisi Concert Hall","lat":41.706832,"lon":44.787076,"vehicleMode":"BUS"},"patternSuffixes":["0:01"]},{"stop":{"id":"1:810","code":"810","name":"Merab Kostava St #47","lat":41.709889,"lon":44.784586,"vehicleMode":"BUS"},"patternSuffixes":["0:01"]},{"stop":{"id":"1:811","code":"811","name":"Heroes Square (Saburtalo direction)","lat":41.714769,"lon":44.784136,"vehicleMode":"BUS"},"patternSuffixes":["0:01"]},{"stop":{"id":"1:2126","code":"2126","name":"Davit Aghmashenebeli Avenue","lat":41.717958,"lon":44.790388,"vehicleMode":"BUS"},"patternSuffixes":["0:01"]},{"stop":{"id":"1:1267","code":"1267","name":"Abastumani Street","lat":41.720977,"lon":44.792901,"vehicleMode":"BUS"},"patternSuffixes":["0:01"]},{"stop":{"id":"1:4585","code":"4585","name":"Boris Paichadze National Stadium","lat":41.722959,"lon":44.791619,"vehicleMode":"BUS"},"patternSuffixes":["0:01"]},{"stop":{"id":"1:4587","code":"4587","name":"M/S \"Tsereteli\"","lat":41.72735,"lon":44.788726,"vehicleMode":"BUS"},"patternSuffixes":["0:01"]},{"stop":{"id":"1:4589","code":"4589","name":"Rajden Gvetadze Street","lat":41.730915,"lon":44.785753,"vehicleMode":"BUS"},"patternSuffixes":["0:01"]},{"stop":{"id":"1:4591","code":"4591","name":"National Screening Center","lat":41.735332,"lon":44.783028,"vehicleMode":"BUS"},"patternSuffixes":["0:01"]},{"stop":{"id":"1:4593","code":"4593","name":"Konstantine Stanislavski Street","lat":41.73956,"lon":44.780523,"vehicleMode":"BUS"},"patternSuffixes":["0:01"]},{"stop":{"id":"1:4595","code":"4595","name":"Tskaltubo Street","lat":41.745373,"lon":44.77813,"vehicleMode":"BUS"},"patternSuffixes":["0:01"]},{"stop":{"id":"1:4597","code":"4597","name":"M/S \"Didube\"","lat":41.74935,"lon":44.777279,"vehicleMode":"BUS"},"patternSuffixes":["0:01"]},{"stop":{"id":"1:1892","code":"1892","name":"Didube District Administration","lat":41.75485,"lon":44.777425,"vehicleMode":"BUS"},"patternSuffixes":["0:01"]},{"stop":{"id":"1:1893","code":"1893","name":"Akaki Beliashvili St #13a","lat":41.757187,"lon":44.779705,"vehicleMode":"BUS"},"patternSuffixes":["0:01"]},{"stop":{"id":"1:3303","code":"3303","name":"Akaki Beliashvili St #23","lat":41.759016,"lon":44.780292,"vehicleMode":"BUS"},"patternSuffixes":["0:01"]},{"stop":{"id":"1:1894","code":"1894","name":"Akaki Beliashvili St #41","lat":41.761607,"lon":44.780332,"vehicleMode":"BUS"},"patternSuffixes":["0:01"]},{"stop":{"id":"1:3304","code":"3304","name":"Akaki Beliashvili St #49","lat":41.763119,"lon":44.780314,"vehicleMode":"BUS"},"patternSuffixes":["0:01"]},{"stop":{"id":"1:3476","code":"3476","name":"Devi Abashidze Street","lat":41.766404,"lon":44.780332,"vehicleMode":"BUS"},"patternSuffixes":["0:01"]},{"stop":{"id":"1:3305","code":"3305","name":"Akaki Beliashvili St #79","lat":41.768163,"lon":44.779885,"vehicleMode":"BUS"},"patternSuffixes":["0:01"]},{"stop":{"id":"1:2604","code":"2604","name":"Akaki Beliashvili St number #99","lat":41.770812,"lon":44.779252,"vehicleMode":"BUS"},"patternSuffixes":["0:01"]},{"stop":{"id":"1:2605","code":"2605","name":"Akaki Beliashvili St #103","lat":41.772616,"lon":44.779842,"vehicleMode":"BUS"},"patternSuffixes":["0:01"]},{"stop":{"id":"1:3306","code":"3306","name":"Akaki Beliashvili St #115","lat":41.775072,"lon":44.780995,"vehicleMode":"BUS"},"patternSuffixes":["0:01"]},{"stop":{"id":"1:3307","code":"3307","name":"Akaki Beliashvili St #145","lat":41.779339,"lon":44.78228,"vehicleMode":"BUS"},"patternSuffixes":["0:01"]},{"stop":{"id":"1:1505","code":"1505","name":"Akaki Beliashvili St #179","lat":41.783521,"lon":44.781851,"vehicleMode":"BUS"},"patternSuffixes":["0:01"]},{"stop":{"id":"1:4572","code":"4572","name":"Georgian-American Friendship Ave #23","lat":41.787305,"lon":44.77816,"vehicleMode":"BUS"},"patternSuffixes":["0:01"]},{"stop":{"id":"1:1537","code":"1537","name":"Georgian-American Friendship Ave #33","lat":41.787485,"lon":44.773428,"vehicleMode":"BUS"},"patternSuffixes":["0:01"]},{"stop":{"id":"1:4267","code":"4267","name":"Anbani Square","lat":41.787509,"lon":44.765682,"vehicleMode":"BUS"},"patternSuffixes":["0:01"]},{"stop":{"id":"1:1180","code":"1180","name":"Giorgi Brtskinvale Street","lat":41.789069,"lon":44.764937,"vehicleMode":"BUS"},"patternSuffixes":["0:01"]},{"stop":{"id":"1:2501","code":"2501","name":"Demetre Tavdadebuli St #21","lat":41.793121,"lon":44.764934,"vehicleMode":"BUS"},"patternSuffixes":["0:01"]},{"stop":{"id":"1:4369","code":"4369","name":"Parnavaz Mepe Ave #47","lat":41.795486,"lon":44.764918,"vehicleMode":"BUS"},"patternSuffixes":["0:01"]},{"stop":{"id":"1:2503","code":"2503","name":"Demetre Tavdadebuli St #2","lat":41.796516,"lon":44.762549,"vehicleMode":"BUS"},"patternSuffixes":["0:01"]},{"stop":{"id":"1:2699","code":"2699","name":"Demetre Tavdadebuli St #18","lat":41.796508,"lon":44.758395,"vehicleMode":"BUS"},"patternSuffixes":["0:01"]},{"stop":{"id":"1:2700","code":"2700","name":"Demetre Tavdadebuli St #30","lat":41.796502,"lon":44.753969,"vehicleMode":"BUS"},"patternSuffixes":["0:01"]},{"stop":{"id":"1:4665","code":"4665","name":"Demetre Tavdadebuli St #39","lat":41.795598,"lon":44.749106,"vehicleMode":"BUS"},"patternSuffixes":["0:01"]},{"stop":{"id":"1:1188","code":"1188","name":"Didi Dighomi IV M/D (Bus Depot #2)","lat":41.795148,"lon":44.745415,"vehicleMode":"BUS"},"patternSuffixes":["0:01"]}]