{"id":"1:R98445","shortName":"316","color":"00B38B","mode":"BUS","patterns":[{"patternSuffix":"1:01","directionId":1,"firstStop":{"id":"1:3932","name":"Nikoloz Baratashvili Street"},"lastStop":{"id":"1:2475","name":"Kiketi, 9 Dzma Kherkheulidze Street"},"headsign":"Kiketi"},{"patternSuffix":"0:01","directionId":0,"firstStop":{"id":"1:2475","name":"Kiketi, 9 Dzma Kherkheulidze Street"},"lastStop":{"id":"1:2994","name":"Elene Akhvlediani Rise"},"headsign":"Baratashvili  St"}],"defaultPatternSuffix":"1:01"}